{"id":"LQJRTUWNQIVGG","name":"IMG_6315-11","size":148041,"btime":1703430318316,"mtime":1703430318349,"ext":"jpg","tags":[],"folders":[],"isDeleted":true,"url":"","annotation":"","modificationTime":1703439386935,"height":1024,"width":1024,"noThumbnail":true,"palettes":[{"color":[223,223,230],"ratio":82,"$$hashKey":"object:1633"},{"color":[128,70,49],"ratio":12,"$$hashKey":"object:1634"},{"color":[154,142,151],"ratio":2.26,"$$hashKey":"object:1635"},{"color":[179,173,187],"ratio":1.61,"$$hashKey":"object:1636"},{"color":[186,188,201],"ratio":0.46,"$$hashKey":"object:1637"}],"deletedTime":1703439551883,"lastModified":1703439551961}