{"id":"LQJRTUWN2UABI","name":"IMG_6332-8","size":60833,"btime":1703431295091,"mtime":1703431295123,"ext":"jpg","tags":[],"folders":[],"isDeleted":true,"url":"","annotation":"","modificationTime":1703439386946,"height":1024,"width":1024,"noThumbnail":true,"palettes":[{"color":[216,221,228],"ratio":97,"$$hashKey":"object:1497"},{"color":[141,137,142],"ratio":1.03,"$$hashKey":"object:1498"},{"color":[174,172,180],"ratio":0.59,"$$hashKey":"object:1499"},{"color":[57,54,56],"ratio":0.33,"$$hashKey":"object:1500"}],"deletedTime":1703439551883,"lastModified":1703439551960}