{"id":"LQKVGS0XRB8JK","name":"IMG_6364-3","size":89892,"btime":1703505439093,"mtime":1703505439129,"ext":"jpg","tags":[],"folders":["LQKVI6XU6AGYA"],"isDeleted":false,"url":"","annotation":"","modificationTime":1703505961188,"height":1024,"width":1024,"noThumbnail":true,"palettes":[{"color":[227,222,219],"ratio":83,"$$hashKey":"object:6256"},{"color":[210,196,187],"ratio":9,"$$hashKey":"object:6257"},{"color":[203,188,180],"ratio":2.62,"$$hashKey":"object:6258"},{"color":[95,40,24],"ratio":2.35,"$$hashKey":"object:6259"},{"color":[201,186,170],"ratio":1.05,"$$hashKey":"object:6260"},{"color":[208,176,63],"ratio":0.75,"$$hashKey":"object:6261"},{"color":[216,194,125],"ratio":0.51,"$$hashKey":"object:6262"}],"lastModified":1703508976367}