{"id":"LQJRTUWNJQZHS","name":"20231216-IMG_6135","size":116862,"btime":1702720394583,"mtime":1702720394631,"ext":"jpg","tags":[],"folders":[],"isDeleted":true,"url":"","annotation":"","modificationTime":1703439386843,"height":1080,"width":1080,"noThumbnail":true,"palettes":[{"color":[231,231,236],"ratio":86,"$$hashKey":"object:2644"},{"color":[68,75,59],"ratio":5,"$$hashKey":"object:2645"},{"color":[143,143,147],"ratio":2.43,"$$hashKey":"object:2646"},{"color":[193,193,207],"ratio":2.38,"$$hashKey":"object:2647"},{"color":[186,185,191],"ratio":1.77,"$$hashKey":"object:2648"},{"color":[165,166,179],"ratio":1.57,"$$hashKey":"object:2649"},{"color":[111,115,122],"ratio":0.46,"$$hashKey":"object:2650"}],"deletedTime":1703439551883,"lastModified":1703439551976}